newsapi/__init__.py
newsapi/cli.py
newsapi/user_settings.py
newsapi/commands/__init__.py
newsapi/commands/base.py
newsapi/commands/headlines.py
newsapi/commands/search.py
newsapi/commands/sources.py
newsapi_cli-1.2.1.dist-info/DESCRIPTION.rst
newsapi_cli-1.2.1.dist-info/METADATA
newsapi_cli-1.2.1.dist-info/RECORD
newsapi_cli-1.2.1.dist-info/WHEEL
newsapi_cli-1.2.1.dist-info/entry_points.txt
newsapi_cli-1.2.1.dist-info/metadata.json
newsapi_cli-1.2.1.dist-info/top_level.txt
