Metadata-Version: 2.0
Name: newsapi-cli
Version: 1.2.1
Summary: A newsapi.org command line program in Python.
Home-page: https://github.com/aziezahmed/newsapi-cli
Author: Aziez Ahmed Chawdhary
Author-email: UNKNOWN
License: MIT License
Keywords: cli,news
Platform: UNKNOWN
Classifier: Intended Audience :: End Users/Desktop
Classifier: Topic :: Utilities
Classifier: License :: Public Domain
Classifier: Natural Language :: English
Classifier: Operating System :: OS Independent
Classifier: Environment :: Console
Classifier: Programming Language :: Python :: 2
Classifier: Programming Language :: Python :: 2.6
Classifier: Programming Language :: Python :: 2.7
Classifier: Programming Language :: Python :: 3
Classifier: Programming Language :: Python :: 3.2
Classifier: Programming Language :: Python :: 3.3
Classifier: Programming Language :: Python :: 3.4
Classifier: Programming Language :: Python :: 3.5
Classifier: Programming Language :: Python :: 3.6
Requires-Dist: configparser
Requires-Dist: docopt
Requires-Dist: requests
Requires-Dist: termcolor
Requires-Dist: unidecode
Provides-Extra: test
Requires-Dist: coverage; extra == 'test'
Requires-Dist: pytest; extra == 'test'
Requires-Dist: pytest-cov; extra == 'test'
